paxx/__init__.py
paxx/cli/__init__.py
paxx/cli/bootstrap.py
paxx/cli/db.py
paxx/cli/deploy.py
paxx/cli/docker.py
paxx/cli/feature.py
paxx/cli/main.py
paxx/cli/start.py
paxx/cli/utils.py
paxx/cli/ext/__init__.py
paxx/cli/ext/commands.py
paxx/cli/infra/__init__.py
paxx/cli/infra/commands.py
paxx/templates/__init__.py
paxx/templates/installer.py
paxx/templates/deploys/linux-server/.env.example.jinja
paxx/templates/deploys/linux-server/README.md.jinja
paxx/templates/deploys/linux-server/build.yml.example.jinja
paxx/templates/deploys/linux-server/deploy-if-changed.sh.jinja
paxx/templates/deploys/linux-server/deploy-init.sh.jinja
paxx/templates/deploys/linux-server/deploy-purge.sh.jinja
paxx/templates/deploys/linux-server/deploy.sh.jinja
paxx/templates/deploys/linux-server/docker-compose.yml.jinja
paxx/templates/deploys/linux-server/get-status.sh.jinja
paxx/templates/deploys/linux-server/server-setup.sh.jinja
paxx/templates/deploys/linux-server/traefik-dynamic.yml.jinja
paxx/templates/ext/__init__.py
paxx/templates/ext/arq/__init__.py
paxx/templates/ext/arq/dependencies.txt
paxx/templates/ext/arq/env.json
paxx/templates/ext/arq/install.py
paxx/templates/ext/arq/templates/arq.py.jinja
paxx/templates/ext/arq/templates/tasks.py.jinja
paxx/templates/ext/postgis/__init__.py
paxx/templates/ext/postgis/dependencies.txt
paxx/templates/ext/postgis/install.py
paxx/templates/ext/postgis/templates/geo.py.jinja
paxx/templates/ext/websocket/__init__.py
paxx/templates/ext/websocket/env.json
paxx/templates/ext/websocket/install.py
paxx/templates/ext/websocket/templates/ws.py.jinja
paxx/templates/features/__init__.py
paxx/templates/features/auth_aws_cognito/SETUP.md
paxx/templates/features/auth_aws_cognito/__init__.py
paxx/templates/features/auth_aws_cognito/config.py
paxx/templates/features/auth_aws_cognito/dependencies.py
paxx/templates/features/auth_aws_cognito/routes.py
paxx/templates/features/auth_aws_cognito/schemas.py
paxx/templates/features/auth_aws_cognito/services.py
paxx-0.2.3.dist-info/METADATA
paxx-0.2.3.dist-info/WHEEL
paxx-0.2.3.dist-info/entry_points.txt
paxx-0.2.3.dist-info/RECORD
