Metadata-Version: 2.4
Name: paxx
Version: 0.2.3
Summary: A domain-oriented FastAPI project scaffolding CLI
Author: Adam
License: MIT
Keywords: domain-driven,fastapi,framework,web
Classifier: Development Status :: 3 - Alpha
Classifier: Framework :: FastAPI
Classifier: Intended Audience :: Developers
Classifier: License :: OSI Approved :: MIT License
Classifier: Programming Language :: Python :: 3
Classifier: Programming Language :: Python :: 3.12
Classifier: Programming Language :: Python :: 3.13
Classifier: Topic :: Internet :: WWW/HTTP :: HTTP Servers
Classifier: Typing :: Typed
Requires-Python: >=3.12
Requires-Dist: jinja2>=3.1.0
Requires-Dist: rich>=13.0.0
Requires-Dist: ruamel-yaml>=0.18.0
Requires-Dist: tomlkit>=0.13.0
Requires-Dist: typer>=0.9.0
Provides-Extra: dev
Requires-Dist: aiosqlite>=0.20.0; extra == 'dev'
Requires-Dist: fastapi>=0.115.0; extra == 'dev'
Requires-Dist: mypy>=1.13.0; extra == 'dev'
Requires-Dist: pre-commit>=4.0.0; extra == 'dev'
Requires-Dist: pydantic-settings>=2.6.0; extra == 'dev'
Requires-Dist: pytest-asyncio>=0.24.0; extra == 'dev'
Requires-Dist: pytest>=8.0.0; extra == 'dev'
Requires-Dist: ruff>=0.8.0; extra == 'dev'
Requires-Dist: sqlalchemy[asyncio]>=2.0.0; extra == 'dev'
Provides-Extra: docs
Requires-Dist: mkdocs-material>=9.5.0; extra == 'docs'
Requires-Dist: mkdocs>=1.6.0; extra == 'docs'
